schemaio/__about__.py
schemaio/__init__.py
schemaio-0.0.1.dist-info/METADATA
schemaio-0.0.1.dist-info/WHEEL
schemaio-0.0.1.dist-info/licenses/LICENSE.txt
schemaio-0.0.1.dist-info/RECORD
