Metadata-Version: 2.1
Name: schemaio
Version: 0.0.1
Project-URL: Documentation, https://github.com/hasansezertasan/schemaio#readme
Project-URL: Issues, https://github.com/hasansezertasan/schemaio/issues
Project-URL: Source, https://github.com/hasansezertasan/schemaio
Author-email: Hasan Sezer Taşan <hasansezertasan@gmail.com>
License-Expression: MIT
License-File: LICENSE.txt
Classifier: Development Status :: 4 - Beta
Classifier: Programming Language :: Python
Classifier: Programming Language :: Python :: 3.8
Classifier: Programming Language :: Python :: 3.9
Classifier: Programming Language :: Python :: 3.10
Classifier: Programming Language :: Python :: 3.11
Classifier: Programming Language :: Python :: 3.12
Classifier: Programming Language :: Python :: Implementation :: CPython
Classifier: Programming Language :: Python :: Implementation :: PyPy
Requires-Python: >=3.8
